aspect_ratio_kd/__init__.py
aspect_ratio_kd/get_version.py
aspect_ratio_kd-0.1.3.dist-info/WHEEL
aspect_ratio_kd-0.1.3.dist-info/METADATA
aspect_ratio_kd-0.1.3.dist-info/RECORD
