Metadata-Version: 2.1
Name: aspect-ratio-kd
Version: 0.1.3
Summary: Aspect Ratio 
Author: Kadir Coşar
Author-email: kadircosarnew@gmail.com
Requires-Python: >=3.6,<4.0
Classifier: Programming Language :: Python :: 3
Classifier: Programming Language :: Python :: 3.10
Classifier: Programming Language :: Python :: 3.6
Classifier: Programming Language :: Python :: 3.7
Classifier: Programming Language :: Python :: 3.8
Classifier: Programming Language :: Python :: 3.9
